pydastic/__init__.py
pydastic/error.py
pydastic/model.py
pydastic/pydastic.py
pydastic/session.py
pydastic-0.4.0.dist-info/LICENSE
pydastic-0.4.0.dist-info/WHEEL
pydastic-0.4.0.dist-info/METADATA
pydastic-0.4.0.dist-info/RECORD
