Metadata-Version: 2.1
Name: pydastic
Version: 0.4.0
Summary: Pydastic is an elasticsearch python ORM based on Pydantic.
Home-page: https://github.com/ramiawar/pydastic
License: MIT
Author: pydastic
Author-email: rami.awar.ra@gmail.com
Requires-Python: >=3.7,<4.0
Classifier: Development Status :: 3 - Alpha
Classifier: Intended Audience :: Developers
Classifier: License :: OSI Approved :: MIT License
Classifier: Operating System :: OS Independent
Classifier: Programming Language :: Python :: 3
Classifier: Programming Language :: Python :: 3.7
Classifier: Programming Language :: Python :: 3.8
Classifier: Programming Language :: Python :: 3.9
Classifier: Topic :: Software Development :: Libraries :: Python Modules
Requires-Dist: elasticsearch (>=7.12.0,<=8.1.2)
Requires-Dist: importlib_metadata (>=4.5.0,<5.0.0); python_version < "3.8"
Requires-Dist: pydantic (>=1.9.0,<2.0.0)
Project-URL: Repository, https://github.com/ramiawar/pydastic
